sqlite_rw/__init__.py
sqlite_rw/async_task.py
sqlite_rw-0.0.2.dist-info/LICENSE
sqlite_rw-0.0.2.dist-info/METADATA
sqlite_rw-0.0.2.dist-info/WHEEL
sqlite_rw-0.0.2.dist-info/top_level.txt
sqlite_rw-0.0.2.dist-info/RECORD
