Metadata-Version: 2.1
Name: sqlite-rw
Version: 0.0.2
Summary: sqlite读写分离库
Home-page: https://github.com/xupingmao/sqlite-rw
Author: mark
Author-email: 578749341@qq.com
Classifier: Programming Language :: Python :: 3
Classifier: License :: OSI Approved :: MIT License
Classifier: Operating System :: OS Independent
License-File: LICENSE
Requires-Dist: web.py (>=0.6.0)
